{"geosearch":{"geosupportReturnCode":"00","bbl":"2024780040"},"addrs":[{"housenumber":"1161","streetname":"STRATFORD AVENUE","zip":"10472","boro":"BRONX","registrationid":201458,"lastregistrationdate":"2019-08-21T00:00:00.000Z","registrationenddate":"2020-09-01T00:00:00.000Z","bbl":"2037430057","bin":2023993,"corpnames":["1163 HOLDING LTD"],"businessaddrs":["1246 SAGE STREET 11691"],"ownernames":[{"title":"HeadOfficer","value":"SOL ZALMAN"},{"title":"Officer","value":"SOL ZALMAN"},{"title":"Agent","value":"SOL ZALMAN"},{"title":"SiteManager","value":"SOL ZALMAN"}],"totalviolations":411,"openviolations":126,"unitsres":70,"yearbuilt":1929,"lat":"40.8280756383526721720045316033065319061279296875","lng":"-73.8755257690879574283826514147222042083740234375","evictions":"1","rsunits2007":64,"rsunits2017":65,"rsdiff":1,"rspercentchange":"1.43"},{"housenumber":"1015","streetname":"LEGGETT AVENUE","zip":"10455","boro":"BRONX","registrationid":202102,"lastregistrationdate":"2019-08-21T00:00:00.000Z","registrationenddate":"2020-09-01T00:00:00.000Z","bbl":"2027200001","bin":2005719,"corpnames":["1272 HOLDING LTD","1272 HOLDING LDT"],"businessaddrs":["1246 SAGE STREET 11691"],"ownernames":[{"title":"Officer","value":"SOL ZALMAN"},{"title":"SiteManager","value":"SOL ZALMAN"},{"title":"Agent","value":"SOL ZALMAN"},{"title":"HeadOfficer","value":"SOL ZALMAN"}],"totalviolations":511,"openviolations":69,"unitsres":50,"yearbuilt":1931,"lat":"40.8142024085155270540781202726066112518310546875","lng":"-73.8993843259418241586899966932833194732666015625","evictions":null,"rsunits2007":46,"rsunits2017":46,"rsdiff":0,"rspercentchange":"0"},{"housenumber":"1466","streetname":"TOWNSEND AVENUE","zip":"10452","boro":"BRONX","registrationid":202843,"lastregistrationdate":"2019-08-21T00:00:00.000Z","registrationenddate":"2020-09-01T00:00:00.000Z","bbl":"2028440043","bin":2008113,"corpnames":["1466 HOLDING LIMITED"],"businessaddrs":["1246 SAGE STREET 11691"],"ownernames":[{"title":"SiteManager","value":"SOL ZALMAN"},{"title":"Agent","value":"SOL ZALMAN"},{"title":"HeadOfficer","value":"SOL ZALMAN"}],"totalviolations":114,"openviolations":45,"unitsres":60,"yearbuilt":1940,"lat":"40.84141811380885656035388819873332977294921875","lng":"-73.9153501033825790500486618839204311370849609375","evictions":null,"rsunits2007":59,"rsunits2017":60,"rsdiff":1,"rspercentchange":"1.67"},{"housenumber":"1113","streetname":"WALTON AVENUE","zip":"10452","boro":"BRONX","registrationid":203609,"lastregistrationdate":"2019-08-21T00:00:00.000Z","registrationenddate":"2020-09-01T00:00:00.000Z","bbl":"2024780040","bin":2002949,"corpnames":["1113 WALTON CO"],"businessaddrs":["1246 SAGE STREET 11691"],"ownernames":[{"title":"HeadOfficer","value":"SOL ZALMAN"},{"title":"Agent","value":"SOL ZALMAN"}],"totalviolations":358,"openviolations":54,"unitsres":61,"yearbuilt":1925,"lat":"40.83310011633415115284151397645473480224609375","lng":"-73.920940190087634391602477990090847015380859375","evictions":"5","rsunits2007":60,"rsunits2017":60,"rsdiff":0,"rspercentchange":"0"},{"housenumber":"1083","streetname":"WALTON AVENUE","zip":"10452","boro":"BRONX","registrationid":203870,"lastregistrationdate":"2019-08-20T00:00:00.000Z","registrationenddate":"2020-09-01T00:00:00.000Z","bbl":"2024780052","bin":2002951,"corpnames":["FINK REALTY CORP"],"businessaddrs":["1246 SAGE STREET 11691"],"ownernames":[{"title":"Officer","value":"SOL ZALMAN"},{"title":"SiteManager","value":"SOL ZALMAN"},{"title":"Agent","value":"SOL ZALMAN"},{"title":"HeadOfficer","value":"SOL ZALMAN"}],"totalviolations":198,"openviolations":44,"unitsres":62,"yearbuilt":1925,"lat":"40.832348366858610688723274506628513336181640625","lng":"-73.9213819458920653460154426284134387969970703125","evictions":"4","rsunits2007":60,"rsunits2017":60,"rsdiff":0,"rspercentchange":"0"},{"housenumber":"2395","streetname":"MORRIS AVENUE","zip":"10468","boro":"BRONX","registrationid":203885,"lastregistrationdate":"2019-08-21T00:00:00.000Z","registrationenddate":"2020-09-01T00:00:00.000Z","bbl":"2031840071","bin":2014040,"corpnames":["2395 HOLDING LTD"],"businessaddrs":["1246 SAGE STREET 11691"],"ownernames":[{"title":"HeadOfficer","value":"SOL ZALMAN"},{"title":"SiteManager","value":"SOL ZALMAN"},{"title":"Officer","value":"SOL ZALMAN"},{"title":"Agent","value":"SOL ZALMAN"}],"totalviolations":546,"openviolations":64,"unitsres":49,"yearbuilt":1922,"lat":"40.86045753399609026246253051795065402984619140625","lng":"-73.9008182519843330737785436213016510009765625","evictions":"2","rsunits2007":48,"rsunits2017":48,"rsdiff":0,"rspercentchange":"0"},{"housenumber":"186","streetname":"EAST 164TH STREET","zip":"10456","boro":"BRONX","registrationid":207438,"lastregistrationdate":"2019-08-14T00:00:00.000Z","registrationenddate":"2020-09-01T00:00:00.000Z","bbl":"2024610070","bin":2002817,"corpnames":["164 REALTY LLC"],"businessaddrs":["1246 SAGE STREET 11691","1997 HUGHES AVENUE OFFICE 10457","5014 16TH AVENUE 190 11204"],"ownernames":[{"title":"Officer","value":"SOL ZALMAN"},{"title":"HeadOfficer","value":"CARL CHAIMS"},{"title":"Agent","value":"CARL CHAIMS"},{"title":"SiteManager","value":"LUIS MENDEZ"}],"totalviolations":718,"openviolations":110,"unitsres":69,"yearbuilt":1949,"lat":"40.82901269262784893498974270187318325042724609375","lng":"-73.9201500886147897517730598337948322296142578125","evictions":"1","rsunits2007":69,"rsunits2017":0,"rsdiff":-69,"rspercentchange":"-100"},{"housenumber":"304","streetname":"EAST 178TH STREET","zip":"10457","boro":"BRONX","registrationid":211140,"lastregistrationdate":"2019-08-21T00:00:00.000Z","registrationenddate":"2020-09-01T00:00:00.000Z","bbl":"2028140029","bin":2007766,"corpnames":["304-306 S&Y REALTY LLC"],"businessaddrs":["304306 EAST 178TH STREET 10457","1246 SAGE STREET 11691","511 AVENUE F 11215"],"ownernames":[{"title":"SiteManager","value":"SOL ZALMAN"},{"title":"HeadOfficer","value":"SOL ZALMAN"},{"title":"Officer","value":"NACHUM FINKELSTEIN"},{"title":"Agent","value":"SOL ZALMAN"}],"totalviolations":430,"openviolations":44,"unitsres":45,"yearbuilt":1926,"lat":"40.8498040812769573904006392695009708404541015625","lng":"-73.90256190475821540530887432396411895751953125","evictions":null,"rsunits2007":43,"rsunits2017":44,"rsdiff":1,"rspercentchange":"2.17"},{"housenumber":"2430","streetname":"MORRIS AVENUE","zip":"10468","boro":"BRONX","registrationid":211175,"lastregistrationdate":"2019-08-21T00:00:00.000Z","registrationenddate":"2020-09-01T00:00:00.000Z","bbl":"2031730020","bin":2013905,"corpnames":["2430 MORRIS AVE ASSOC LLC"],"businessaddrs":["1246 SAGE STREET 11691"],"ownernames":[{"title":"SiteManager","value":"RAFAEL RIVERA"},{"title":"HeadOfficer","value":"SOL ZALMAN"},{"title":"Agent","value":"SOL ZALMAN"}],"totalviolations":508,"openviolations":44,"unitsres":53,"yearbuilt":1924,"lat":"40.86126630736743692295931396074593067169189453125","lng":"-73.8997614075792768062456161715090274810791015625","evictions":null,"rsunits2007":0,"rsunits2017":51,"rsdiff":51,"rspercentchange":"96.23"}]}