{"geosearch":{"geosupportReturnCode":"00","bbl":"2025080031"},"addrs":[{"housenumber":"1035","streetname":"ANDERSON AVENUE","zip":"10452","boro":"BRONX","registrationid":215676,"lastregistrationdate":"2012-10-01T00:00:00.000Z","registrationenddate":"2013-09-15T00:00:00.000Z","bbl":"2025080031","bin":2003143,"corpnames":["B CROOMS, M. FORD, J CARSON, A HARRIS"],"businessaddrs":["1323 COMMON WEALTH AVENUE 10472","5 CHAMIN PLACE 07631"],"ownernames":[{"title":"SiteManager","value":"JOSEPH BENJAMIN"},{"title":"Officer","value":"BERNICE CROOMS"},{"title":"Agent","value":"JOSEPH CARSON"}],"totalviolations":355,"openviolations":24,"unitsres":53,"yearbuilt":2014,"lat":"40.83314518130605819123957189731299877166748046875","lng":"-73.92684126041871195411658845841884613037109375","evictions":"1","rsunits2007":0,"rsunits2017":53,"rsdiff":53,"rspercentchange":"100"}]}