{"result":[{"bldgs":"35","units":"643","age":"92.9","topowners":["ISSAKA MAIGUZO","DENNIS RIVERA","GABRIEL GARCIA","GUILLERMO MALENA","FRANKLIN RODRIGUEZ"],"topcorp":"1970 UNIVERSITY LLC","topbusinessaddr":"36 WEST 37TH STREET 10018","totalopenviolations":"1670","totalviolations":"14503","openviolationsperbldg":"47.7","openviolationsperresunit":"2.6","totalevictions":"37","avgevictions":"1.1","totalrsgain":"3","totalrsloss":"-378","totalrsdiff":"-375","avgrspercent":"-61.3","rsproportion":"58.3","rslossaddr":{"housenumber":"1841","streetname":"DR M L KING JR BOULEVARD","boro":"BRONX","lat":40.85174321267378,"lng":-73.91468632048887,"rsdiff":-58},"evictionsaddr":{"housenumber":"1970","streetname":"DR M L KING JR BOULEVARD","boro":"BRONX","lat":40.85419446562551,"lng":-73.91135393213979,"evictions":5},"violationsaddr":{"housenumber":"133","streetname":"WEST 145TH STREET","boro":"MANHATTAN","lat":40.82116788001824,"lng":-73.93723824691192,"openviolations":193}}]}