{"geosearch":{"geosupportReturnCode":"00","bbl":"2031020037"},"addrs":[{"housenumber":"281","streetname":"EDGECOMBE AVENUE","zip":"10031","boro":"MANHATTAN","registrationid":127594,"lastregistrationdate":"2019-09-24T00:00:00.000Z","registrationenddate":"2020-09-01T00:00:00.000Z","bbl":"1020530014","bin":1061126,"corpnames":["281 EDGECOMBE PARTNERS,LLC"],"businessaddrs":["1325 CASTLE HILL AVENUE 10462"],"ownernames":[{"title":"HeadOfficer","value":"HOWARD ALKOFF"},{"title":"SiteManager","value":"CANDIDO RAMIREZ"},{"title":"Officer","value":"AIDA SPITZER"},{"title":"Agent","value":"DORA GENAO"}],"totalviolations":109,"openviolations":9,"unitsres":49,"yearbuilt":1920,"lat":"40.82459104325184995332165271975100040435791015625","lng":"-73.943514769195900271370192058384418487548828125","evictions":"1","rsunits2007":45,"rsunits2017":49,"rsdiff":4,"rspercentchange":"8.16"},{"housenumber":"224","streetname":"EAST 164TH STREET","zip":"10456","boro":"BRONX","registrationid":202606,"lastregistrationdate":"2019-09-10T00:00:00.000Z","registrationenddate":"2020-09-01T00:00:00.000Z","bbl":"2024460018","bin":2002483,"corpnames":["BROWNSTONE FAMILY HOLDING LLC"],"businessaddrs":["1325 CASTLE HILL AVENUE 10462"],"ownernames":[{"title":"Agent","value":"DORA GENAO"},{"title":"SiteManager","value":"TOMAS AGUILAR"},{"title":"Officer","value":"GARY PERLOW"},{"title":"HeadOfficer","value":"HOWARD ALKOFF"}],"totalviolations":11,"openviolations":0,"unitsres":22,"yearbuilt":1905,"lat":"40.8288742634488386329394415952265262603759765625","lng":"-73.9184447116799248078677919693291187286376953125","evictions":null,"rsunits2007":20,"rsunits2017":20,"rsdiff":0,"rspercentchange":"0"},{"housenumber":"2363","streetname":"PROSPECT AVENUE","zip":"10458","boro":"BRONX","registrationid":203060,"lastregistrationdate":"2019-09-10T00:00:00.000Z","registrationenddate":"2020-09-01T00:00:00.000Z","bbl":"2031020037","bin":2012840,"corpnames":["D & A EQUITIES INC"],"businessaddrs":["1325 CASTLE HILL AVENUE 10462"],"ownernames":[{"title":"Agent","value":"DORA GENAO"},{"title":"SiteManager","value":"LUIS SOTO"},{"title":"Officer","value":"GARY PERLOW"},{"title":"HeadOfficer","value":"HOWARD ALKOFF"}],"totalviolations":13,"openviolations":4,"unitsres":26,"yearbuilt":1916,"lat":"40.85324995386992696921879542060196399688720703125","lng":"-73.8832323277752749390856479294598102569580078125","evictions":null,"rsunits2007":27,"rsunits2017":27,"rsdiff":0,"rspercentchange":"0"},{"housenumber":"2357","streetname":"PROSPECT AVENUE","zip":"10458","boro":"BRONX","registrationid":203259,"lastregistrationdate":"2019-09-10T00:00:00.000Z","registrationenddate":"2020-09-01T00:00:00.000Z","bbl":"2031020039","bin":2012841,"corpnames":["BROWNSTONE FAMILY HOLDINGLLC"],"businessaddrs":["1325 CASTLE HILL AVENUE 10462"],"ownernames":[{"title":"SiteManager","value":"LUIS SOTO"},{"title":"Agent","value":"DORA GENAO"},{"title":"HeadOfficer","value":"HOWARD ALKOFF"},{"title":"Officer","value":"GARY PERLOW"}],"totalviolations":54,"openviolations":0,"unitsres":61,"yearbuilt":1926,"lat":"40.8530579236011277544093900360167026519775390625","lng":"-73.88333026325864238970098085701465606689453125","evictions":null,"rsunits2007":61,"rsunits2017":62,"rsdiff":1,"rspercentchange":"1.61"},{"housenumber":"1181","streetname":"SHERIDAN AVENUE","zip":"10456","boro":"BRONX","registrationid":204324,"lastregistrationdate":"2019-09-24T00:00:00.000Z","registrationenddate":"2020-09-01T00:00:00.000Z","bbl":"2024560175","bin":2002751,"corpnames":["H & H EQUITIES II INC"],"businessaddrs":["1325 CASTLE HILL AVENUE 10462"],"ownernames":[{"title":"HeadOfficer","value":"HOWARD ALKOFF"},{"title":"Officer","value":"GARY PERLOW"},{"title":"SiteManager","value":"ARELIS LIRIANO"},{"title":"Agent","value":"DORA GENAO"}],"totalviolations":28,"openviolations":0,"unitsres":68,"yearbuilt":1936,"lat":"40.83346274033039691175872576422989368438720703125","lng":"-73.917481459875460814146208576858043670654296875","evictions":"2","rsunits2007":67,"rsunits2017":67,"rsdiff":0,"rspercentchange":"0"},{"housenumber":"185","streetname":"MC CLELLAN STREET","zip":"10456","boro":"BRONX","registrationid":204330,"lastregistrationdate":"2019-09-10T00:00:00.000Z","registrationenddate":"2020-09-01T00:00:00.000Z","bbl":"2024560181","bin":2002752,"corpnames":["H & H EQUITIES INC"],"businessaddrs":["1325 CASTLE HILL AVENUE 10462"],"ownernames":[{"title":"Officer","value":"GARY PERLOW"},{"title":"Agent","value":"DORA GENAO"},{"title":"SiteManager","value":"MODESTO PEREZ"},{"title":"HeadOfficer","value":"HOWARD ALKOFF"}],"totalviolations":96,"openviolations":1,"unitsres":111,"yearbuilt":1936,"lat":"40.83304300606349812596818082965910434722900390625","lng":"-73.9177710736669126845299615524709224700927734375","evictions":null,"rsunits2007":117,"rsunits2017":117,"rsdiff":0,"rspercentchange":"0"},{"housenumber":"1860","streetname":"MORRIS AVENUE","zip":"10453","boro":"BRONX","registrationid":204357,"lastregistrationdate":"2019-09-10T00:00:00.000Z","registrationenddate":"2020-09-01T00:00:00.000Z","bbl":"2028050001","bin":2007615,"corpnames":["1860 MORRIS ASSOCIATES"],"businessaddrs":["1325 CASTLE HILL AVENUE 10462"],"ownernames":[{"title":"SiteManager","value":"YOLANDA MARIZAN"},{"title":"HeadOfficer","value":"ALAN ALKOFF"},{"title":"Officer","value":"AMY CHASIN"},{"title":"Agent","value":"DORA GENAO"}],"totalviolations":27,"openviolations":0,"unitsres":67,"yearbuilt":1931,"lat":"40.84824423122083913995084003545343875885009765625","lng":"-73.908210025393572095708805136382579803466796875","evictions":null,"rsunits2007":69,"rsunits2017":69,"rsdiff":0,"rspercentchange":"0"},{"housenumber":"2025","streetname":"WALTON AVENUE","zip":"10453","boro":"BRONX","registrationid":204358,"lastregistrationdate":"2019-09-10T00:00:00.000Z","registrationenddate":"2020-09-01T00:00:00.000Z","bbl":"2028540056","bin":2008269,"corpnames":["2025 WALTON ASSOCIATES LLC"],"businessaddrs":["1325 CASTLE HILL AVENUE 10462"],"ownernames":[{"title":"SiteManager","value":"JOSUE DE LA CRUZ"},{"title":"Agent","value":"DORA GENAO"},{"title":"HeadOfficer","value":"HOWARD ALKOFF"},{"title":"Officer","value":"ARELIS ALKOFF"}],"totalviolations":55,"openviolations":0,"unitsres":65,"yearbuilt":1951,"lat":"40.853024704481782691800617612898349761962890625","lng":"-73.9072057568867109011989668942987918853759765625","evictions":null,"rsunits2007":59,"rsunits2017":59,"rsdiff":0,"rspercentchange":"0"},{"housenumber":"1915","streetname":"MORRIS AVENUE","zip":"10453","boro":"BRONX","registrationid":205254,"lastregistrationdate":"2019-09-10T00:00:00.000Z","registrationenddate":"2020-09-01T00:00:00.000Z","bbl":"2028280030","bin":2007918,"corpnames":["1915 MORRIS AVE CORP"],"businessaddrs":["1325 CASTLE HILL AVENUE 10462"],"ownernames":[{"title":"Agent","value":"DORA GENAO"},{"title":"SiteManager","value":"MARGIE PIZARRO"},{"title":"Officer","value":"AMY CHASIN"},{"title":"HeadOfficer","value":"HOWARD ALKOFF"}],"totalviolations":0,"openviolations":0,"unitsres":55,"yearbuilt":1939,"lat":"40.85020394052421721653445274569094181060791015625","lng":"-73.908196477262805501595721580088138580322265625","evictions":null,"rsunits2007":55,"rsunits2017":55,"rsdiff":0,"rspercentchange":"0"},{"housenumber":"2388","streetname":"TIEBOUT AVENUE","zip":"10458","boro":"BRONX","registrationid":205313,"lastregistrationdate":"2019-09-10T00:00:00.000Z","registrationenddate":"2020-09-01T00:00:00.000Z","bbl":"2030220010","bin":2010980,"corpnames":["2390 TIEBOUT ASSOCIATES LLC"],"businessaddrs":["1325 CASTLE HILL AVENUE 10462"],"ownernames":[{"title":"HeadOfficer","value":"HOWARD ALKOFF"},{"title":"Agent","value":"DORA GENAO"},{"title":"SiteManager","value":"RUBEN HERNANDEZ"},{"title":"Officer","value":"ARELIS ALKOFF"}],"totalviolations":24,"openviolations":2,"unitsres":57,"yearbuilt":1937,"lat":"40.85899841848520708254000055603682994842529296875","lng":"-73.8957990870073757605496211908757686614990234375","evictions":null,"rsunits2007":57,"rsunits2017":57,"rsdiff":0,"rspercentchange":"0"},{"housenumber":"212","streetname":"EAST 178TH STREET","zip":"10457","boro":"BRONX","registrationid":205629,"lastregistrationdate":"2019-09-10T00:00:00.000Z","registrationenddate":"2020-09-01T00:00:00.000Z","bbl":"2028100013","bin":2007724,"corpnames":["214 EAST 178 STREET CORP"],"businessaddrs":["1325 CASTLE HILL AVENUE 10462"],"ownernames":[{"title":"Officer","value":"HOWARD ALKOFF"},{"title":"SiteManager","value":"WINY HERNANDEZ"},{"title":"Agent","value":"DORA GENAO"},{"title":"HeadOfficer","value":"GARY PERLOW"}],"totalviolations":14,"openviolations":0,"unitsres":30,"yearbuilt":1951,"lat":"40.85018167180357551160341245122253894805908203125","lng":"-73.904433712803211165009997785091400146484375","evictions":null,"rsunits2007":30,"rsunits2017":30,"rsdiff":0,"rspercentchange":"0"},{"housenumber":"2256","streetname":"WALTON AVENUE","zip":"10453","boro":"BRONX","registrationid":205802,"lastregistrationdate":"2019-09-10T00:00:00.000Z","registrationenddate":"2020-09-01T00:00:00.000Z","bbl":"2031820008","bin":2013989,"corpnames":["H G 2256 WALTON CORP"],"businessaddrs":["1325 CASTLE HILL AVENUE 10462","1325 CASTLE HILL AVENUE 14062"],"ownernames":[{"title":"HeadOfficer","value":"AMY CHASIN"},{"title":"SiteManager","value":"DIEGO QUINONES"},{"title":"Officer","value":"ALAN ALKOFF"},{"title":"Agent","value":"DORA GENAO"}],"totalviolations":32,"openviolations":0,"unitsres":43,"yearbuilt":1926,"lat":"40.85749786717655496204315568320453166961669921875","lng":"-73.90301335231907842171494849026203155517578125","evictions":null,"rsunits2007":42,"rsunits2017":42,"rsdiff":0,"rspercentchange":"0"},{"housenumber":"935","streetname":"OGDEN AVENUE","zip":"10452","boro":"BRONX","registrationid":205814,"lastregistrationdate":"2019-09-24T00:00:00.000Z","registrationenddate":"2020-09-01T00:00:00.000Z","bbl":"2025240018","bin":2003442,"corpnames":["935 OGDEN AVE CORP"],"businessaddrs":["1325 CASTLE HILL AVENUE 10462"],"ownernames":[{"title":"SiteManager","value":"REGINA RODRIGUEZ"},{"title":"Officer","value":"ARELIS ALKOFF"},{"title":"HeadOfficer","value":"HOWARD ALKOFF"},{"title":"Agent","value":"DORA GENAO"}],"totalviolations":7,"openviolations":0,"unitsres":29,"yearbuilt":1928,"lat":"40.8314786715676945050290669314563274383544921875","lng":"-73.9305217170656447933652088977396488189697265625","evictions":null,"rsunits2007":28,"rsunits2017":28,"rsdiff":0,"rspercentchange":"0"},{"housenumber":"1816","streetname":"ANTHONY AVENUE","zip":"10457","boro":"BRONX","registrationid":208188,"lastregistrationdate":"2019-09-10T00:00:00.000Z","registrationenddate":"2020-09-01T00:00:00.000Z","bbl":"2028920011","bin":2009371,"corpnames":["ANTHONY EQUITIES,LTD"],"businessaddrs":["1325 CASTLE HILL AVENUE 10462"],"ownernames":[{"title":"SiteManager","value":"FELIX ROMAN"},{"title":"Agent","value":"DORA GENAO"},{"title":"HeadOfficer","value":"HOWARD ALKOFF"},{"title":"Officer","value":"AMY CHASIN"}],"totalviolations":6,"openviolations":0,"unitsres":72,"yearbuilt":1956,"lat":"40.846686758186507404388976283371448516845703125","lng":"-73.9033507973398826607080991379916667938232421875","evictions":null,"rsunits2007":72,"rsunits2017":72,"rsdiff":0,"rspercentchange":"0"},{"housenumber":"2805","streetname":"POND PLACE","zip":"10458","boro":"BRONX","registrationid":208190,"lastregistrationdate":"2019-09-10T00:00:00.000Z","registrationenddate":"2020-09-01T00:00:00.000Z","bbl":"2032900042","bin":2016719,"corpnames":["POND PLACE PROPERTIES LLC"],"businessaddrs":["1325 CASTLE HILL AVENUE 10462"],"ownernames":[{"title":"Agent","value":"DORA GENAO"},{"title":"SiteManager","value":"LIDIA RIVERA"},{"title":"Officer","value":"ALAN ALKOFF"},{"title":"HeadOfficer","value":"AMY CHASIN"}],"totalviolations":13,"openviolations":0,"unitsres":61,"yearbuilt":1954,"lat":"40.86772780394863957553752698004245758056640625","lng":"-73.888322910743937654842738993465900421142578125","evictions":null,"rsunits2007":60,"rsunits2017":60,"rsdiff":0,"rspercentchange":"0"},{"housenumber":"651","streetname":"CRESCENT AVENUE","zip":"10458","boro":"BRONX","registrationid":209363,"lastregistrationdate":"2019-09-10T00:00:00.000Z","registrationenddate":"2020-09-01T00:00:00.000Z","bbl":"2030740037","bin":2012169,"corpnames":["BROWNSTONE FAMILY HOLDING LLC"],"businessaddrs":["1325 CASTLE HILL AVENUE 10462"],"ownernames":[{"title":"HeadOfficer","value":"HOWARD ALKOFF"},{"title":"SiteManager","value":"ADRIANO HENRIQUEZ"},{"title":"Officer","value":"GARY PERLOW"},{"title":"Agent","value":"DORA GENAO"}],"totalviolations":4,"openviolations":2,"unitsres":24,"yearbuilt":1913,"lat":"40.8542138671832475438350229524075984954833984375","lng":"-73.8865056596616369688490522094070911407470703125","evictions":null,"rsunits2007":27,"rsunits2017":27,"rsdiff":0,"rspercentchange":"0"},{"housenumber":"2180","streetname":"ANTHONY AVENUE","zip":"10457","boro":"BRONX","registrationid":220980,"lastregistrationdate":"2019-09-10T00:00:00.000Z","registrationenddate":"2020-09-01T00:00:00.000Z","bbl":"2031570017","bin":2013705,"corpnames":["ANTHONY EQUITIES II LTD"],"businessaddrs":["1325 CASTLE HILL AVENUE 10462"],"ownernames":[{"title":"HeadOfficer","value":"HOWARD ALKOFF"},{"title":"Officer","value":"AMY CHASIN"},{"title":"SiteManager","value":"YBELKA BAEZ"},{"title":"Agent","value":"DORA GENAO"}],"totalviolations":7,"openviolations":0,"unitsres":38,"yearbuilt":1959,"lat":"40.85509427782716329602408222854137420654296875","lng":"-73.9006924997498089169312152080237865447998046875","evictions":null,"rsunits2007":38,"rsunits2017":38,"rsdiff":0,"rspercentchange":"0"},{"housenumber":"80","streetname":"MC CLELLAN STREET","zip":"10452","boro":"BRONX","registrationid":221639,"lastregistrationdate":"2019-09-10T00:00:00.000Z","registrationenddate":"2020-09-01T00:00:00.000Z","bbl":"2024780030","bin":2002948,"corpnames":["MC CLELLAN EQUITIES LLC"],"businessaddrs":["1325 CASTLE HILL AVENUE 10462"],"ownernames":[{"title":"Agent","value":"DORA GENAO"},{"title":"SiteManager","value":"LUIS LIRIANO"},{"title":"Officer","value":"ARELIS ALKOFF"},{"title":"HeadOfficer","value":"HOWARD ALKOFF"}],"totalviolations":6,"openviolations":0,"unitsres":103,"yearbuilt":1966,"lat":"40.833481616278930914631928317248821258544921875","lng":"-73.9209180546252042631749645806849002838134765625","evictions":"1","rsunits2007":103,"rsunits2017":103,"rsdiff":0,"rspercentchange":"0"}]}