{"result":[{"bldgs":"6","units":"112","age":"102.8","topowners":["JERRY TROIANOS","VASILIKI TROIANOS","NOAH JACHARO","JOHN ZERVOUDIS","KALLIOPE ZERVOUDIS"],"topcorp":"VASZER REALTY LLC","topbusinessaddr":"530 150TH STREET 11357","totalopenviolations":"288","totalviolations":"923","openviolationsperbldg":"48.0","openviolationsperresunit":"2.6","totalevictions":"1","avgevictions":"0.2","totalrsgain":"0","totalrsloss":"-105","totalrsdiff":"-105","avgrspercent":"-86.8","rsproportion":"93.8","rslossaddr":{"housenumber":"353","streetname":"EAST MOSHOLU PARKWAY NORTH","boro":"BRONX","lat":40.87120792221863,"lng":-73.87996470470169,"rsdiff":-25},"evictionsaddr":{"housenumber":"1965","streetname":"WEBSTER AVENUE","boro":"BRONX","lat":40.84939322155491,"lng":-73.90033955583861,"evictions":1},"violationsaddr":{"housenumber":"3034","streetname":"32ND STREET","boro":"QUEENS","lat":40.76573667794825,"lng":-73.92156165691276,"openviolations":103}}]}