{"result":[{"bldgs":"8","units":"43","age":"100.1","topowners":["SEAN SEDAGHATPOUR","SEAN SED","SEAN JOSHUA"],"topcorp":"36 HENDRIX LLC","topbusinessaddr":"350 NORTHERN BOULEVARD 310 11021","totalopenviolations":"115","totalviolations":"180","openviolationsperbldg":"14.4","openviolationsperresunit":"2.7","totalevictions":null,"avgevictions":null,"totalrsgain":"20","totalrsloss":"0","totalrsdiff":"20","avgrspercent":"50.0","rsproportion":"46.5","rslossaddr":{"housenumber":"406","streetname":"TOMPKINS AVENUE","boro":"BROOKLYN","lat":40.683385165701495,"lng":-73.94417881780797,"rsdiff":0},"evictionsaddr":{"housenumber":"406","streetname":"TOMPKINS AVENUE","boro":"BROOKLYN","lat":40.683385165701495,"lng":-73.94417881780797,"evictions":null},"violationsaddr":{"housenumber":"107","streetname":"JEFFERSON AVENUE","boro":"BROOKLYN","lat":40.683169536080825,"lng":-73.9530269993764,"openviolations":55}}]}