{"result":[{"bldgs":"2","units":"8","age":"90.5","topowners":["BEN RASABI","BAROUCH ABARGEL","ASAF YEMINI","ALPHA PHILMON"],"topcorp":"145-11 JAMAICA AVE. CORP","topbusinessaddr":"14511 JAMAICA AVENUE 11435","totalopenviolations":"22","totalviolations":"111","openviolationsperbldg":"11.0","openviolationsperresunit":"2.8","totalevictions":null,"avgevictions":null,"totalrsgain":"0","totalrsloss":"0","totalrsdiff":"0","avgrspercent":"0.0","rsproportion":"0.0","rslossaddr":{"housenumber":"110","streetname":"COOPER STREET","boro":"BROOKLYN","lat":40.68655699573198,"lng":-73.9081910145393,"rsdiff":0},"evictionsaddr":{"housenumber":"110","streetname":"COOPER STREET","boro":"BROOKLYN","lat":40.68655699573198,"lng":-73.9081910145393,"evictions":null},"violationsaddr":{"housenumber":"14511","streetname":"JAMAICA AVENUE","boro":"QUEENS","lat":40.70216897559619,"lng":-73.80949364361115,"openviolations":15}}]}